kicksaw_lambda_logger/__init__.py
kicksaw_lambda_logger-0.0.1.dist-info/WHEEL
kicksaw_lambda_logger-0.0.1.dist-info/METADATA
kicksaw_lambda_logger-0.0.1.dist-info/RECORD
