Metadata-Version: 2.1
Name: kicksaw-lambda-logger
Version: 0.0.1
Summary: A customized loger for seamlessly logging on an AWS Lambda or local environment, with reporting in Sentry and other logging-related featues
Home-page: https://github.com/Kicksaw-Consulting/kicksaw-lambda-logger
Keywords: kicksaw,aws,lambda,logging
Author: Alex Drozd
Author-email: alex@kicksaw.com
Requires-Python: >=3.8,<4.0
Classifier: Programming Language :: Python :: 3
Classifier: Programming Language :: Python :: 3.10
Classifier: Programming Language :: Python :: 3.8
Classifier: Programming Language :: Python :: 3.9
Requires-Dist: sentry-sdk (>=1.5.0,<2.0.0)
Project-URL: Repository, https://github.com/Kicksaw-Consulting/kicksaw-lambda-logger
